Workbook

Sheet Click Events Tagged
A1: event_name | B1: Frequency | C1: Quantity
A2: $VIDEOS$VID$ABOUT_ASBL$BTN$LIKE$CLICK | B2: Used Occasionally | C2: Used by few
A3: $VIDEOS$VID$ABOUT_ASBL$BTN$SHARE$CLICK | B3: Used Occasionally | C3: Used by few
A4: $VIDEOS$VID$AJITESH_KORUPOLU_BEER_BICEPS_PODCAST$BTN$SHARE$CLICK | B4: Used Frequently | C4: Used by few
A5: $VIDEOS$VID$DEC24_LOFT_ROTC$BTN$LIKE$CLICK | B5: Used Rarely | C5: Used by few
A6: $VIDEOS$VID$DEC24_LOFT_ROTC$BTN$SHARE$CLICK | B6: Used Rarely | C6: Used by few
A7: $VIDEOS$VID$GACHIBOWLI_CIRCLE_TO_ASBL_LOFT$BTN$SHARE$CLICK | B7: Used Occasionally | C7: Used by some
A8: $VIDEOS$VID$LOFT_PROGRESS_REPORT$BTN$LIKE$CLICK | B8: Used Occasionally | C8: Used by few
A9: $VIDEOS$VID$LOFT_PROGRESS_REPORT$BTN$UNLIKE$CLICK | B9: Used Rarely | C9: Used by few
A10: $VIDEOS$VID$THE_KEY_TO_ENVY$BTN$LIKE$CLICK | B10: Used Occasionally | C10: Used by some
A11: $VIDEOS$VID$THE_KEY_TO_ENVY$BTN$SHARE$CLICK | B11: Used Occasionally | C11: Used by some
A12: $VIDEOS$VID$THE_KEY_TO_ENVY$BTN$UNLIKE$CLICK | B12: Used Occasionally | C12: Used by few
... A920: VIDEOS$ZERO_BURDEN_OFFER$VIDEO_SEEK_START | B920: Used Frequently | C920: Used by some

Sheet Missing Events
A1: Missing Click Events in the Event List | B1: Missing ViewEvent
A2: $VIDEOS$VID$ABOUT_ASBL$BTN$UNLIKE$CLICK | B2: AMENITIES$ENQUIRY_DIALOG
A3: $VIDEOS$VID$AJITESH_KORUPOLU_RAJ_SHAMANI_PODCAST$BTN$SHARE$CLICK | B3: HOME$BROCHURE_SECTION$ENQUIRY_DIALOG
A4: $VIDEOS$VID$AJITESH_KORUPOLU_RAJ_VK_PODCAST$BTN$SHARE$CLICK | B4: HOME$HERO_SECTION
A5: $VIDEOS$VID$ASBL_ROTC_Unveiling_ASBL_Loft$BTN$LIKE$CLICK | B5: LOCATION$CONNECT_WITH_US$ENQUIRY_DIALOG
A6: $VIDEOS$VID$ASBL_ROTC_Unveiling_ASBL_Loft$BTN$SHARE$CLICK | B6: LOCATION$MAPS$ENQUIRY_DIALOG
A7: $VIDEOS$VID$ASBL_ROTC_Unveiling_ASBL_Loft$BTN$UNLIKE$CLICK | B7: LOCATION$MAPS$WHATSAPP_DIALOG
A8: $VIDEOS$VID$CEO_VISION$BTN$LIKE$CLICK | B8: MEDIA$ENQUIRY_DIALOG
A9: $VIDEOS$VID$CEO_VISION$BTN$SHARE$CLICK | B9: MEDIA$EVENTS$WHATSAPP_ENQUIRY_DIALOG
A10: $VIDEOS$VID$GACHIBOWLI_CIRCLE_TO_ASBL_LOFT$BTN$LIKE$CLICK | B10: MEDIA$KEY_TO_ENVY_SECTION
A11: $VIDEOS$VID$GRANULARITY_OF_DATA$BTN$LIKE$CLICK | B11: MEDIA$VIDEOS$ENQUIRY_DIALOG
A12: $VIDEOS$VID$GRANULARITY_OF_DATA$BTN$UNLIKE$CLICK | B12: MEDIA$VIDEOS$WHATSAPP_DIALOG
... A37: AMENITIES$WHATSAPP_DIALOG$SUBMIT_LEAD_BTN | B37: SPECIFICATION$RELATED_SEARCH_SECTION
A38: HOME$BROCHURE_SECTION$ENQUIRY_DIALOG$AMENITIES_BTN
A39: HOME$BROCHURE_SECTION$ENQUIRY_DIALOG$GET_IMMEDIATE_ASSISTANCE_BTN
A40: HOME$BROCHURE_SECTION$ENQUIRY_DIALOG$LOCATION_BTN
A41: HOME$BROCHURE_SECTION$ENQUIRY_DIALOG$PLANS_BTN
A42: HOME$BROCHURE_SECTION$ENQUIRY_DIALOG$PRICE_BTN
A43: HOME$BROCHURE_SECTION$ENQUIRY_DIALOG$SPECIFICATIONS_BTN
A44: HOME$BROCHURE_SECTION$ENQUIRY_DIALOG$VIDEOS_BTN
A45: HOME$BROCHURE_SECTION$ENQUIRY_DIALOG$ZIPCODE_SUBMITTED
A46: HOME$ENQUIRY_BTN
A47: HOME$ENQUIRY_DIALOG$AMENITIES_BTN
A48: HOME$ENQUIRY_DIALOG$GET_IMMEDIATE_ASSISTANCE_BTN
A49: HOME$ENQUIRY_DIALOG$LEAD_CREATED
... A358: VIDEOS$THREE_PILLERS_OF_ASBL$VIDEO_FULL_SCREEN_OPEN

Sheet Click Events
A1: ViewEvent | B1: Frequency | C1: Quantity
A2: $VIDEOS$VID$ABOUT_ASBL$BTN$LIKE$CLICK | B2: =VLOOKUP(A2,'Click Events Tagged'!A:C,2,FALSE) -> Used Occasionally | C2: =VLOOKUP(A2,'Click Events Tagged'!A:C,3,FALSE) -> Used by few
A3: $VIDEOS$VID$ABOUT_ASBL$BTN$SHARE$CLICK | B3: =VLOOKUP(A3,'Click Events Tagged'!A:C,2,FALSE) -> Used Occasionally | C3: =VLOOKUP(A3,'Click Events Tagged'!A:C,3,FALSE) -> Used by few
A4: $VIDEOS$VID$ABOUT_ASBL$BTN$UNLIKE$CLICK | B4: =VLOOKUP(A4,'Click Events Tagged'!A:C,2,FALSE) -> #N/A | C4: =VLOOKUP(A4,'Click Events Tagged'!A:C,3,FALSE) -> #N/A
A5: $VIDEOS$VID$AJITESH_KORUPOLU_RAJ_SHAMANI_PODCAST$BTN$SHARE$CLICK | B5: =VLOOKUP(A5,'Click Events Tagged'!A:C,2,FALSE) -> #N/A | C5: =VLOOKUP(A5,'Click Events Tagged'!A:C,3,FALSE) -> #N/A
A6: $VIDEOS$VID$AJITESH_KORUPOLU_RAJ_VK_PODCAST$BTN$SHARE$CLICK | B6: =VLOOKUP(A6,'Click Events Tagged'!A:C,2,FALSE) -> #N/A | C6: =VLOOKUP(A6,'Click Events Tagged'!A:C,3,FALSE) -> #N/A
A7: $VIDEOS$VID$ASBL_ROTC_Unveiling_ASBL_Loft$BTN$LIKE$CLICK | B7: =VLOOKUP(A7,'Click Events Tagged'!A:C,2,FALSE) -> #N/A | C7: =VLOOKUP(A7,'Click Events Tagged'!A:C,3,FALSE) -> #N/A
A8: $VIDEOS$VID$ASBL_ROTC_Unveiling_ASBL_Loft$BTN$SHARE$CLICK | B8: =VLOOKUP(A8,'Click Events Tagged'!A:C,2,FALSE) -> #N/A | C8: =VLOOKUP(A8,'Click Events Tagged'!A:C,3,FALSE) -> #N/A
A9: $VIDEOS$VID$ASBL_ROTC_Unveiling_ASBL_Loft$BTN$UNLIKE$CLICK | B9: =VLOOKUP(A9,'Click Events Tagged'!A:C,2,FALSE) -> #N/A | C9: =VLOOKUP(A9,'Click Events Tagged'!A:C,3,FALSE) -> #N/A
A10: $VIDEOS$VID$CEO_VISION$BTN$LIKE$CLICK | B10: =VLOOKUP(A10,'Click Events Tagged'!A:C,2,FALSE) -> #N/A | C10: =VLOOKUP(A10,'Click Events Tagged'!A:C,3,FALSE) -> #N/A
A11: $VIDEOS$VID$CEO_VISION$BTN$SHARE$CLICK | B11: =VLOOKUP(A11,'Click Events Tagged'!A:C,2,FALSE) -> #N/A | C11: =VLOOKUP(A11,'Click Events Tagged'!A:C,3,FALSE) -> #N/A
A12: $VIDEOS$VID$GACHIBOWLI_CIRCLE_TO_ASBL_LOFT$BTN$LIKE$CLICK | B12: =VLOOKUP(A12,'Click Events Tagged'!A:C,2,FALSE) -> #N/A | C12: =VLOOKUP(A12,'Click Events Tagged'!A:C,3,FALSE) -> #N/A
A13: $VIDEOS$VID$GACHIBOWLI_CIRCLE_TO_ASBL_LOFT$BTN$SHARE$CLICK | B13: =VLOOKUP(A13,'Click Events Tagged'!A:C,2,FALSE) -> Used Occasionally | C13: =VLOOKUP(A13,'Click Events Tagged'!A:C,3,FALSE) -> Used by some
... A880: VIDEOS$VIRTUAL_TOURS_PLAYLIST_CHIP | B880: =VLOOKUP(A880,'Click Events Tagged'!A:C,2,FALSE) -> Used Occasionally | C880: =VLOOKUP(A880,'Click Events Tagged'!A:C,3,FALSE) -> Used by some

Sheet View Events
A1: ViewEvent | B1: Frequency | C1: Quantity
A2: AMENITIES$ARRIVAL_EXPERIENCE_SECTION$CLUB_HOUSE | B2: =VLOOKUP(A2,'View Events Tagged'!A:C,2,FALSE) -> Used Frequently | C2: =VLOOKUP(A2,'View Events Tagged'!A:C,3,FALSE) -> Used by many
A3: AMENITIES$ARRIVAL_EXPERIENCE_SECTION$GRAND_ENTRANCE | B3: =VLOOKUP(A3,'View Events Tagged'!A:C,2,FALSE) -> Used Frequently | C3: =VLOOKUP(A3,'View Events Tagged'!A:C,3,FALSE) -> Used by many
A4: AMENITIES$CHILDCARE_SECTION$CHILDCARE_AMENITIES | B4: =VLOOKUP(A4,'View Events Tagged'!A:C,2,FALSE) -> Used Frequently | C4: =VLOOKUP(A4,'View Events Tagged'!A:C,3,FALSE) -> Used by some
A5: AMENITIES$CHILDCARE_SECTION$CRECHE_SPACE | B5: =VLOOKUP(A5,'View Events Tagged'!A:C,2,FALSE) -> Used Frequently | C5: =VLOOKUP(A5,'View Events Tagged'!A:C,3,FALSE) -> Used by some
A6: AMENITIES$ENQUIRE_NOW_SECTION | B6: =VLOOKUP(A6,'View Events Tagged'!A:C,2,FALSE) -> Used Frequently | C6: =VLOOKUP(A6,'View Events Tagged'!A:C,3,FALSE) -> Used by some
A7: AMENITIES$ENQUIRY_DIALOG | B7: =VLOOKUP(A7,'View Events Tagged'!A:C,2,FALSE) -> #N/A | C7: =VLOOKUP(A7,'View Events Tagged'!A:C,3,FALSE) -> #N/A
A8: AMENITIES$FITNESS_SECTION$EXQUISITE_FACILITIES | B8: =VLOOKUP(A8,'View Events Tagged'!A:C,2,FALSE) -> Used Frequently | C8: =VLOOKUP(A8,'View Events Tagged'!A:C,3,FALSE) -> Used by many
A9: AMENITIES$FITNESS_SECTION$HEALTH_AND_FITNESS | B9: =VLOOKUP(A9,'View Events Tagged'!A:C,2,FALSE) -> Used Frequently | C9: =VLOOKUP(A9,'View Events Tagged'!A:C,3,FALSE) -> Used by many
A10: AMENITIES$FITNESS_SECTION$SWIMMING_POOL | B10: =VLOOKUP(A10,'View Events Tagged'!A:C,2,FALSE) -> Used Frequently | C10: =VLOOKUP(A10,'View Events Tagged'!A:C,3,FALSE) -> Used by some
A11: AMENITIES$FITNESS_SECTION$YOGA_FITNESS_ROOM | B11: =VLOOKUP(A11,'View Events Tagged'!A:C,2,FALSE) -> Used Frequently | C11: =VLOOKUP(A11,'View Events Tagged'!A:C,3,FALSE) -> Used by some
A12: AMENITIES$FOOTER_SECTION | B12: =VLOOKUP(A12,'View Events Tagged'!A:C,2,FALSE) -> Used Frequently | C12: =VLOOKUP(A12,'View Events Tagged'!A:C,3,FALSE) -> Used by some
A13: AMENITIES$GUEST_EXPERIENCE_SECTION$GUEST_ROOM | B13: =VLOOKUP(A13,'View Events Tagged'!A:C,2,FALSE) -> Used Frequently | C13: =VLOOKUP(A13,'View Events Tagged'!A:C,3,FALSE) -> Used by some
... A170: VIDEOS$VIDEO_PLAYER | B170: =VLOOKUP(A170,'View Events Tagged'!A:C,2,FALSE) -> Used Always | C170: =VLOOKUP(A170,'View Events Tagged'!A:C,3,FALSE) -> Used by some

Sheet View Events Tagged
A1: event_name | B1: Frequency | C1: Quantity
A2: AMENITIES$ARRIVAL_EXPERIENCE_SECTION$CLUB_HOUSE | B2: Used Frequently | C2: Used by many
A3: AMENITIES$ARRIVAL_EXPERIENCE_SECTION$GRAND_ENTRANCE | B3: Used Frequently | C3: Used by many
A4: AMENITIES$BOOK_A_SITE_VISIT | B4: Used Frequently | C4: Used by some
A5: AMENITIES$CHILDCARE_SECTION$CHILDCARE_AMENITIES | B5: Used Frequently | C5: Used by some
A6: AMENITIES$CHILDCARE_SECTION$CRECHE_SPACE | B6: Used Frequently | C6: Used by some
A7: AMENITIES$ENQUIRE_NOW_SECTION | B7: Used Frequently | C7: Used by some
A8: AMENITIES$FITNESS_SECTION$EXQUISITE_FACILITIES | B8: Used Frequently | C8: Used by many
A9: AMENITIES$FITNESS_SECTION$HEALTH_AND_FITNESS | B9: Used Frequently | C9: Used by many
A10: AMENITIES$FITNESS_SECTION$SWIMMING_POOL | B10: Used Frequently | C10: Used by some
A11: AMENITIES$FITNESS_SECTION$YOGA_FITNESS_ROOM | B11: Used Frequently | C11: Used by some
A12: AMENITIES$FOOTER_SECTION | B12: Used Frequently | C12: Used by some
... A290: VIDEOS$VIDEO_PLAYER | B290: Used Always | C290: Used by some

Sheet Event Count
A1: Click Events | D1: View Events | H1: Frequency Tagging Criteria
H2: Used Always
A3: Row Labels | B3: Count of event_name | D3: Row Labels | E3: Count of event_name | H3: Condition: For almost every lead who used the event (say ≥80–90%), it was repeated at least twice in their journey.
A4: Used Always | B4: 11 | D4: Used Always | E4: 19 | H4: Interpretation: This event is a core “hub”, leads keep coming back to it (like Home).
A5: Used Frequently | B5: 158 | D5: Used Frequently | E5: 210 | H5: Used Frequently
A6: Used Occasionally | B6: 694 | D6: Used Occasionally | E6: 52 | H6: Condition: For a large share of leads (around 50–80%), the event appears multiple times, while others only use it once.
A7: Used Rarely | B7: 56 | D7: Used Rarely | E7: 8 | H7: Interpretation: Important touchpoint, but not universally repeated.
A8: Grand Total | B8: 919 | D8: Grand Total | E8: 289 | H8: Used Occasionally
H9: Condition: For most leads who use the event (≥70%), it appears only once.
H10: Interpretation: Something users check once in their journey (like Location map).
A11: Row Labels | B11: Count of event_name | D11: Row Labels | E11: Count of event_name | H11: Used Rarely
A12: Used by few | B12: 228 | D12: Used by few | E12: 70 | H12: Condition: Event is triggered by very few leads overall (tiny adoption, e.g. <10–15% of all leads).
A13: Used by many | B13: 230 | D13: Used by many | E13: 73 | H13: Interpretation: A niche or low-engagement event.
A14: Used by some | B14: 461 | D14: Used by some | E14: 146
A15: Grand Total | B15: 919 | D15: Grand Total | E15: 289
H16: Quantity Tagging Criteria
H17: Used by few → very small % of total leads (say <10%).
A18: Frequency = how each lead personally repeats the event. | H18: Used by some → moderate % (10–40%).
A19: Quantity = how many leads in total touched it. | H19: Used by many → large share (40–90%).
H20: Used by all → literally every lead has it.
